odoo/addons/l10n_hr_base/README.rst
odoo/addons/l10n_hr_base/__init__.py
odoo/addons/l10n_hr_base/__manifest__.py
odoo/addons/l10n_hr_base/i18n/hr.po
odoo/addons/l10n_hr_base/i18n/l10n_hr_base.pot
odoo/addons/l10n_hr_base/models/__init__.py
odoo/addons/l10n_hr_base/models/l10n_hr_xml_common.py
odoo/addons/l10n_hr_base/models/res_company.py
odoo/addons/l10n_hr_base/models/res_partner.py
odoo/addons/l10n_hr_base/static/description/icon.png
odoo/addons/l10n_hr_base/views/res_company_view.xml
odoo_addon_l10n_hr_base-16.0.1.0.1.dist-info/METADATA
odoo_addon_l10n_hr_base-16.0.1.0.1.dist-info/WHEEL
odoo_addon_l10n_hr_base-16.0.1.0.1.dist-info/top_level.txt
odoo_addon_l10n_hr_base-16.0.1.0.1.dist-info/RECORD
